adafruit_ble_creation.py
adafruit_circuitpython_ble_creation-0.9.9.dist-info/LICENSE
adafruit_circuitpython_ble_creation-0.9.9.dist-info/METADATA
adafruit_circuitpython_ble_creation-0.9.9.dist-info/WHEEL
adafruit_circuitpython_ble_creation-0.9.9.dist-info/top_level.txt
adafruit_circuitpython_ble_creation-0.9.9.dist-info/RECORD
